disai/__init__.py
disai/disai_jazz/__init__.py
disai/disai_jazz/agent.py
disai/disai_jazz/arch.py
disai/disai_jazz/openai_model.py
disai/disai_jazz/task.py
disai/disai_jazz/utils.py
disai/disai_jazza/__init__.py
disai/disai_jazza/arch.py
disai_agents-0.3839.dist-info/METADATA
disai_agents-0.3839.dist-info/WHEEL
disai_agents-0.3839.dist-info/top_level.txt
disai_agents-0.3839.dist-info/RECORD
